pyweii/cli.py
pyweii-0.1.1.dist-info/LICENSE
pyweii-0.1.1.dist-info/entry_points.txt
pyweii-0.1.1.dist-info/METADATA
pyweii-0.1.1.dist-info/WHEEL
pyweii-0.1.1.dist-info/RECORD
