Metadata-Version: 2.1
Name: pyweii
Version: 0.1.1
Summary: A utility to measure weight using the Wii Balance Board.
Home-page: https://gitlab.com/stavros/weii
License: AGPL-3.0-or-later
Author: Stavros Korokithakis
Author-email: hi@stavros.io
Requires-Python: >=3.8,<4
Classifier: License :: OSI Approved :: GNU Affero General Public License v3 or later (AGPLv3+)
Classifier: Programming Language :: Python :: 3
Classifier: Programming Language :: Python :: 3.8
Classifier: Programming Language :: Python :: 3.9
Classifier: Programming Language :: Python :: 3.10
Classifier: Programming Language :: Python :: 3.11
Requires-Dist: evdev (>=1.6.1,<2.0.0)
Project-URL: Repository, https://gitlab.com/stavros/weii
